x_tools/utils/__init__.py
x_tools/utils/cfg_toml.py
x_tools/utils/utils.py
x_tools/utils/models/__init__.py
x_tools/utils/models/mdl_git_repos.py
x_tools/utils/models/tp_file_path.py
x_tools_utils-0.2.0.dist-info/METADATA
x_tools_utils-0.2.0.dist-info/WHEEL
x_tools_utils-0.2.0.dist-info/top_level.txt
x_tools_utils-0.2.0.dist-info/RECORD
