Metadata-Version: 2.4
Name: x_tools-utils
Version: 0.2.0
Summary: Base utilities for x_tools_splt packages.
Author-email: Milan Brzoň <milan.brzon@generaliceska.cz>
Requires-Python: >=3.9
Requires-Dist: tomli~=2.2.1
Requires-Dist: pydantic~=2.11.7
Requires-Dist: tabulate~=0.9.0
